Adyan/__init__.py
Adyan/Utils/H5_TK.py
Adyan/Utils/Mongo_conn.py
Adyan/Utils/MyUtils.py
Adyan/Utils/Rabbit_conn.py
Adyan/Utils/Redis_conn.py
Adyan/Utils/__init__.py
Adyan/Utils/logger.py
Adyan/Utils/monitor_rabbit.py
Adyan/Utils/my_middleware.py
Adyan/Utils/proxy.py
Adyan/config_mongo/__init__.py
Adyan/config_mongo/settings.py
Adyan/login/__init__.py
Adyan/login/cookies.py
Adyan/login/login.py
Adyan/proxy/__init__.py
Adyan/proxy/proxy.py
Adyan/proxy/scheduler.py
Adyan_test-0.2.9.dist-info/LICENSE
Adyan_test-0.2.9.dist-info/METADATA
Adyan_test-0.2.9.dist-info/WHEEL
Adyan_test-0.2.9.dist-info/top_level.txt
Adyan_test-0.2.9.dist-info/RECORD
